maps_generator/__init__.py
maps_generator/__main__.py
maps_generator/check_logs.py
maps_generator/check_mwms.py
maps_generator/diff_stats.py
maps_generator/maps_generator.py
maps_generator/update_generation_order.py
maps_generator/checks/__init__.py
maps_generator/checks/check.py
maps_generator/checks/check_addresses.py
maps_generator/checks/check_categories.py
maps_generator/checks/check_log_levels.py
maps_generator/checks/check_mwm_types.py
maps_generator/checks/check_sections.py
maps_generator/checks/check_size.py
maps_generator/checks/default_check_set.py
maps_generator/generator/__init__.py
maps_generator/generator/coastline.py
maps_generator/generator/env.py
maps_generator/generator/exceptions.py
maps_generator/generator/gen_tool.py
maps_generator/generator/generation.py
maps_generator/generator/osmtools.py
maps_generator/generator/settings.py
maps_generator/generator/stages.py
maps_generator/generator/stages_declaration.py
maps_generator/generator/stages_tests.py
maps_generator/generator/statistics.py
maps_generator/generator/status.py
maps_generator/generator/steps.py
maps_generator/utils/__init__.py
maps_generator/utils/algo.py
maps_generator/utils/file.py
maps_generator/utils/log.py
maps_generator/utils/md5.py
maps_generator/utils/system.py
maps_generator/var/etc/file_generation_order.txt
maps_generator/var/etc/map_generator.ini.default
maps_generator/var/etc/stats_types_config.txt
omim_maps_generator-10.3.0rc2.dist-info/METADATA
omim_maps_generator-10.3.0rc2.dist-info/WHEEL
omim_maps_generator-10.3.0rc2.dist-info/top_level.txt
omim_maps_generator-10.3.0rc2.dist-info/RECORD
