Metadata-Version: 2.1
Name: omim-maps-generator
Version: 10.3.0rc2
Summary: This package contains tools for maps generation.
Home-page: https://github.com/mapsme
Author: My.com B.V. (Mail.Ru Group)
Author-email: dev@maps.me
License: UNKNOWN
Platform: UNKNOWN
Classifier: Programming Language :: Python :: 3
Classifier: License :: OSI Approved :: Apache Software License
Requires-Python: >=3.6
Requires-Dist: omim-data-all (==10.3.0rc2)
Requires-Dist: omim-data-files (==10.3.0rc2)
Requires-Dist: omim-descriptions (==10.3.0rc2)
Requires-Dist: omim-post-generation (==10.3.0rc2)
Requires-Dist: filelock (==3.0.10)
Requires-Dist: beautifulsoup4 (==4.9.1)
Requires-Dist: requests (==2.23.0)
Requires-Dist: requests-file (==1.5.1)
